[
  {
    "sha": "ffb182611cb01220bbbf5c752414b073268d2588",
    "author": "FullMaury",
    "commit": {
      "date": "2026-03-05T14:18:45.000Z",
      "message": "feat: ingresar y mostrar cant de items",
      "url": "https://github.com/MauricioGarron/Proy-ingsoft-totalizadorVentas/commit/ffb182611cb01220bbbf5c752414b073268d2588"
    },
    "stats": {
      "total": 69,
      "additions": 36,
      "deletions": 33,
      "date": "2026-03-05"
    },
    "coverage": 100,
    "test_count": 2,
    "failed_tests": 0,
    "conclusion": "success"
  },
  {
    "sha": "e965cecf008ea2bd757346e342d82fe33811fc70",
    "author": "Mauricio",
    "commit": {
      "date": "2026-03-07T06:03:27.000Z",
      "message": "refactor: cambio y orden en carpetas",
      "url": "https://github.com/MauricioGarron/Proy-ingsoft-totalizadorVentas/commit/e965cecf008ea2bd757346e342d82fe33811fc70"
    },
    "stats": {
      "total": 4,
      "additions": 2,
      "deletions": 2,
      "date": "2026-03-07"
    },
    "coverage": 100,
    "test_count": 2,
    "failed_tests": 0,
    "conclusion": "success"
  },
  {
    "sha": "db6a9325bfdefc50a3ac9318fa8b0be79864797c",
    "author": "Mauricio",
    "commit": {
      "date": "2026-03-07T06:09:51.000Z",
      "message": "fix: error de carpetas",
      "url": "https://github.com/MauricioGarron/Proy-ingsoft-totalizadorVentas/commit/db6a9325bfdefc50a3ac9318fa8b0be79864797c"
    },
    "stats": {
      "total": 15,
      "additions": 15,
      "deletions": 0,
      "date": "2026-03-07"
    },
    "coverage": 100,
    "test_count": 4,
    "failed_tests": 0,
    "conclusion": "success"
  },
  {
    "sha": "96df4dad3b97c64f32817e051024a602a83d279c",
    "author": "Mauricio",
    "commit": {
      "date": "2026-03-07T06:17:44.000Z",
      "message": "feat: precio por item",
      "url": "https://github.com/MauricioGarron/Proy-ingsoft-totalizadorVentas/commit/96df4dad3b97c64f32817e051024a602a83d279c"
    },
    "stats": {
      "total": 32,
      "additions": 21,
      "deletions": 11,
      "date": "2026-03-07"
    },
    "coverage": 100,
    "test_count": 4,
    "failed_tests": 0,
    "conclusion": "success"
  },
  {
    "sha": "a6543541d268296672c22527e1c1e5d0954b1eaf",
    "author": "Mauricio",
    "commit": {
      "date": "2026-03-07T06:22:24.000Z",
      "message": "feat: funcionalidad de descuento por monto",
      "url": "https://github.com/MauricioGarron/Proy-ingsoft-totalizadorVentas/commit/a6543541d268296672c22527e1c1e5d0954b1eaf"
    },
    "stats": {
      "total": 25,
      "additions": 24,
      "deletions": 1,
      "date": "2026-03-07"
    },
    "coverage": 85.71,
    "test_count": 6,
    "failed_tests": 0,
    "conclusion": "success"
  },
  {
    "sha": "a62707089c6f38c6a5a2404058d74810e9f7ebd9",
    "author": "Mauricio",
    "commit": {
      "date": "2026-03-07T06:46:45.000Z",
      "message": "feat: agregar descuento e impuesto",
      "url": "https://github.com/MauricioGarron/Proy-ingsoft-totalizadorVentas/commit/a62707089c6f38c6a5a2404058d74810e9f7ebd9"
    },
    "stats": {
      "total": 83,
      "additions": 75,
      "deletions": 8,
      "date": "2026-03-07"
    },
    "coverage": 90,
    "test_count": 9,
    "failed_tests": 0,
    "conclusion": "success"
  },
  {
    "sha": "7e73112cdf32627c131eed1192796221291c73ec",
    "author": "Mauricio",
    "commit": {
      "date": "2026-03-08T14:10:34.000Z",
      "message": "refactor: mejoras de codigo en presenter con descuentos",
      "url": "https://github.com/MauricioGarron/Proy-ingsoft-totalizadorVentas/commit/7e73112cdf32627c131eed1192796221291c73ec"
    },
    "stats": {
      "total": 54,
      "additions": 45,
      "deletions": 9,
      "date": "2026-03-08"
    },
    "coverage": 92.31,
    "test_count": 13,
    "failed_tests": 0,
    "conclusion": "success"
  },
  {
    "sha": "72b13a87c3d2212e227f9b264949d40f869697e1",
    "author": "Mauricio",
    "commit": {
      "date": "2026-03-08T17:15:43.000Z",
      "message": "feat: implementar descuento adicional por categoria",
      "url": "https://github.com/MauricioGarron/Proy-ingsoft-totalizadorVentas/commit/72b13a87c3d2212e227f9b264949d40f869697e1"
    },
    "stats": {
      "total": 16,
      "additions": 15,
      "deletions": 1,
      "date": "2026-03-08"
    },
    "coverage": 92.31,
    "test_count": 13,
    "failed_tests": 0,
    "conclusion": "success"
  },
  {
    "sha": "7839df36f0dd6b50cd201872b969be513cad7c20",
    "author": "Grizzz88",
    "commit": {
      "date": "2026-03-09T18:18:37.000Z",
      "message": "Aplicar impuesto adicional por categoria",
      "url": "https://github.com/MauricioGarron/Proy-ingsoft-totalizadorVentas/commit/7839df36f0dd6b50cd201872b969be513cad7c20"
    },
    "stats": {
      "total": 14084,
      "additions": 4285,
      "deletions": 9799,
      "date": "2026-03-09"
    },
    "coverage": 93.75,
    "test_count": 18,
    "failed_tests": 0,
    "conclusion": "success"
  },
  {
    "sha": "6f2e112a38dc3f981cd321b96379d6cc294c8fa1",
    "author": "Grizzz88",
    "commit": {
      "date": "2026-03-09T18:47:12.000Z",
      "message": "permitir ingresar peso volumetrico por unidad",
      "url": "https://github.com/MauricioGarron/Proy-ingsoft-totalizadorVentas/commit/6f2e112a38dc3f981cd321b96379d6cc294c8fa1"
    },
    "stats": {
      "total": 42,
      "additions": 42,
      "deletions": 0,
      "date": "2026-03-09"
    },
    "coverage": 93.75,
    "test_count": 25,
    "failed_tests": 7,
    "conclusion": "failure"
  },
  {
    "sha": "fde8ba9058e1dfe4b726d6bafd18c1a694fa4b18",
    "author": "Grizzz88",
    "commit": {
      "date": "2026-03-09T18:54:25.000Z",
      "message": "feat: implementacion de calculo de costo de envio por unidad por peso volumetrico",
      "url": "https://github.com/MauricioGarron/Proy-ingsoft-totalizadorVentas/commit/fde8ba9058e1dfe4b726d6bafd18c1a694fa4b18"
    },
    "stats": {
      "total": 17,
      "additions": 16,
      "deletions": 1,
      "date": "2026-03-09"
    },
    "coverage": 96.55,
    "test_count": 25,
    "failed_tests": 0,
    "conclusion": "success"
  },
  {
    "sha": "HEAD",
    "author": "Grizzz88",
    "commit": {
      "date": "2026-03-09T19:13:13.000Z",
      "message": "feat: implementar calculo de costo total de envio",
      "url": "https://github.com/MauricioGarron/Proy-ingsoft-totalizadorVentas/commit/HEAD"
    },
    "stats": {
      "total": 26,
      "additions": 23,
      "deletions": 3,
      "date": "2026-03-09"
    },
    "coverage": 96.67,
    "test_count": 27,
    "failed_tests": 0,
    "conclusion": "success"
  }
]